xcodeproj/__init__.py
xcodeproj/buildphases.py
xcodeproj/buildrules.py
xcodeproj/files.py
xcodeproj/objects.py
xcodeproj/other.py
xcodeproj/pathobjects.py
xcodeproj/pbxobject.py
xcodeproj/pbxproject.py
xcodeproj/schemes.py
xcodeproj/targets.py
xcodeproj/xcobjects.py
xcodeproj-2.2.4.dist-info/LICENSE
xcodeproj-2.2.4.dist-info/METADATA
xcodeproj-2.2.4.dist-info/WHEEL
xcodeproj-2.2.4.dist-info/RECORD
