Metadata-Version: 2.1
Name: xcodeproj
Version: 2.2.4
Summary: A utility for interacting with Xcode's xcodeproj bundle format.
Home-page: https://github.com/Microsoft/xcodeproj
License: MIT
Keywords: xcode,xcodeproj,pbxproj,apple
Author: Dale Myers
Author-email: dalemy@microsoft.com
Requires-Python: >=3.10,<4.0
Classifier: Development Status :: 4 - Beta
Classifier: Intended Audience :: Developers
Classifier: License :: OSI Approved :: MIT License
Classifier: Programming Language :: Python :: 3
Classifier: Programming Language :: Python :: 3.10
Classifier: Programming Language :: Python :: 3.11
Classifier: Programming Language :: Python :: 3.12
Classifier: Programming Language :: Python :: 3.13
Classifier: Topic :: Software Development
Classifier: Topic :: Utilities
Requires-Dist: deserialize (>=2.0.1,<3.0.0)
Requires-Dist: platformdirs (>=4.5.0,<5.0.0)
Project-URL: Repository, https://github.com/Microsoft/xcodeproj
